Metadata-Version: 2.1
Name: odoo14-addon-datev-export
Version: 14.0.1.0.1.dev4
Summary: Export invoices and refunds as xml and pdf files zipped in DATEV format.
Home-page: https://github.com/OCA/l10n-germany
Author: Guenter Selbert, Thorsten Vocks, Maciej Wichowski, Daniela Scarpa, Maria Sparenberg, initOS GmbH, Odoo Community Association (OCA)
Author-email: support@odoo-community.org
License: AGPL-3
Platform: UNKNOWN
Classifier: Programming Language :: Python
Classifier: Framework :: Odoo
Classifier: Framework :: Odoo :: 14.0
Classifier: License :: OSI Approved :: GNU Affero General Public License v3
Requires-Python: >=3.6
Requires-Dist: odoo <14.1dev,>=14.0a
